{
  "entries": {
    "brew": {
      "watchman": {
        "version": "4.9.0_4",
        "bottle": {
          "cellar": "/usr/local/Cellar",
          "prefix": "/usr/local",
          "files": {
            "catalina": {
              "url": "https://homebrew.bintray.com/bottles/watchman-4.9.0_4.catalina.bottle.tar.gz",
              "sha256": "7840f564c11d33425c9eb8985f9156e782e66ef2a3578329dba83ee15a9bf0be"
            },
            "mojave": {
              "url": "https://homebrew.bintray.com/bottles/watchman-4.9.0_4.mojave.bottle.tar.gz",
              "sha256": "ba2338b0f23c8b8817fd7bfa92466b7a97ab416e93ec6c3a400041aef013de86"
            },
            "high_sierra": {
              "url": "https://homebrew.bintray.com/bottles/watchman-4.9.0_4.high_sierra.bottle.tar.gz",
              "sha256": "150468653b5c5a8e4eb92a3ecf420f157ed0e4772513ee93425bb3f635964dad"
            }
          }
        }
      }
    }
  },
  "system": {
    "macos": {
      "catalina": {
        "HOMEBREW_VERSION": "2.4.16-156-g39f0784",
        "HOMEBREW_PREFIX": "/usr/local",
        "Homebrew/homebrew-core": "98ce016cf817beea3ddfb9b57e3c97e342f9da23",
        "CLT": "1103.0.32.29",
        "Xcode": "11.6",
        "macOS": "10.15.6"
      }
    }
  }
}
